README.md
setup.py
baseproxy/__init__.py
baseproxy/proxy.py
baseproxy.egg-info/PKG-INFO
baseproxy.egg-info/SOURCES.txt
baseproxy.egg-info/dependency_links.txt
baseproxy.egg-info/requires.txt
baseproxy.egg-info/top_level.txt
test/testca.py
test/testhttps.py