Metadata-Version: 1.1
Name: baseproxy
Version: 1.0.1
Summary: Asynchronous HTTP/HTTPS proxy that intercepts and modifies messages(异步http/https代理,可拦截修改报文)
Home-page: https://github.com/qiyeboy/BaseProxy
Author: qiye
Author-email: qiye_email@qq.com
License: GPLv2
Download-URL: https://github.com/qiyeboy/BaseProxy
Platform: UNKNOWN
